django_listable-0.9.3.dist-info/licenses/AUTHORS.rst
django_listable-0.9.3.dist-info/licenses/LICENSE
listable/__init__.py
listable/models.py
listable/settings.py
listable/utils.py
listable/views.py
listable/static/listable/css/bootstrap-datepicker.min.css
listable/static/listable/css/bootstrap.multiselect.css
listable/static/listable/css/daterangepicker.css
listable/static/listable/css/demo_page.css
listable/static/listable/css/demo_table.css
listable/static/listable/css/demo_table_jui.css
listable/static/listable/css/font-awesome.min.css
listable/static/listable/css/jquery.dataTables.bootstrap.css
listable/static/listable/css/jquery.dataTables.css
listable/static/listable/css/jquery.dataTables_themeroller.css
listable/static/listable/css/listable.css
listable/static/listable/fonts/fontawesome-webfont.svg
listable/static/listable/img/back_disabled.png
listable/static/listable/img/back_enabled.png
listable/static/listable/img/back_enabled_hover.png
listable/static/listable/img/forward_disabled.png
listable/static/listable/img/forward_enabled.png
listable/static/listable/img/forward_enabled_hover.png
listable/static/listable/img/sort_asc.png
listable/static/listable/img/sort_asc_disabled.png
listable/static/listable/img/sort_both.png
listable/static/listable/img/sort_desc.png
listable/static/listable/img/sort_desc_disabled.png
listable/static/listable/js/bootstrap-datepicker.min.js
listable/static/listable/js/bootstrap.multiselect.js
listable/static/listable/js/dataTables.bootstrap.js
listable/static/listable/js/dataTables.bootstrap.min.js
listable/static/listable/js/daterangepicker.js
listable/static/listable/js/jquery.dataTables.bootstrap.js
listable/static/listable/js/jquery.dataTables.columnFilter.js
listable/static/listable/js/jquery.dataTables.js
listable/static/listable/js/jquery.dataTables.min.js
listable/static/listable/js/jquery.dataTables.searchPlugins.js
listable/static/listable/js/jquery.dataTables.sort.js
listable/static/listable/js/jquery.js
listable/static/listable/js/listable.js
listable/static/listable/js/moment.js
django_listable-0.9.3.dist-info/METADATA
django_listable-0.9.3.dist-info/WHEEL
django_listable-0.9.3.dist-info/top_level.txt
django_listable-0.9.3.dist-info/RECORD
